{"C:\\Git\\Game\\Content\\Table\\PVPRank.xlsx":{"CachedLastWriteTime":"2023-08-10T02:17:19.4568624+09:00","FilePath":"C:\\Git\\Game\\Content\\Table\\PVPRank.xlsx","RowCount":24,"ColumnCount":4,"LastRecordIndex":24,"ColumnHeaders":[],"ResourceColums":[],"RecordIndexToDataArrayIndex":null,"ForeignKeyInfoMap":{},"CommentColumns":[],"IndexColumn":{"EnumName":null,"DataType":0,"MachineType":0,"StructType":0,"ColumnIndex":0,"Name":null}},"C:\\Git\\Game\\Content\\Table\\JourneyBuffGroup.xlsx":{"CachedLastWriteTime":"2023-04-24T10:21:41.4875756+09:00","FilePath":"C:\\Git\\Game\\Content\\Table\\JourneyBuffGroup.xlsx","RowCount":43,"ColumnCount":16,"LastRecordIndex":3,"ColumnHeaders":[],"ResourceColums":[],"RecordIndexToDataArrayIndex":null,"ForeignKeyInfoMap":{},"CommentColumns":[],"IndexColumn":{"EnumName":null,"DataType":0,"MachineType":0,"StructType":0,"ColumnIndex":0,"Name":null}},"C:\\Git\\Game\\Content\\Table\\MonsterMultiplayDifficulty.xlsx":{"CachedLastWriteTime":"2023-04-21T17:24:18.8292984+09:00","FilePath":"C:\\Git\\Game\\Content\\Table\\MonsterMultiplayDifficulty.xlsx","RowCount":12,"ColumnCount":19,"LastRecordIndex":3,"ColumnHeaders":[],"ResourceColums":[],"RecordIndexToDataArrayIndex":null,"ForeignKeyInfoMap":{},"CommentColumns":[],"IndexColumn":{"EnumName":null,"DataType":0,"MachineType":0,"StructType":0,"ColumnIndex":0,"Name":null}},"C:\\Git\\Game\\Content\\Table\\SkillAbility.xlsx":{"CachedLastWriteTime":"2024-01-11T10:42:28.3750256+09:00","FilePath":"C:\\Git\\Game\\Content\\Table\\SkillAbility.xlsx","RowCount":2608,"ColumnCount":34,"LastRecordIndex":2608,"ColumnHeaders":[],"ResourceColums":[],"RecordIndexToDataArrayIndex":null,"ForeignKeyInfoMap":{},"CommentColumns":[],"IndexColumn":{"EnumName":null,"DataType":0,"MachineType":0,"StructType":0,"ColumnIndex":0,"Name":null}},"C:\\Git\\Game\\Content\\Table\\JourneyLevelReward.xlsx":{"CachedLastWriteTime":"2023-04-14T16:47:47.154936+09:00","FilePath":"C:\\Git\\Game\\Content\\Table\\JourneyLevelReward.xlsx","RowCount":17,"ColumnCount":12,"LastRecordIndex":17,"ColumnHeaders":[],"ResourceColums":[],"RecordIndexToDataArrayIndex":null,"ForeignKeyInfoMap":{},"CommentColumns":[],"IndexColumn":{"EnumName":null,"DataType":0,"MachineType":0,"StructType":0,"ColumnIndex":0,"Name":null}},"C:\\Git\\Game\\Content\\Table\\UserPreset.xlsx":{"CachedLastWriteTime":"2023-01-04T10:39:12.6574099+09:00","FilePath":"C:\\Git\\Game\\Content\\Table\\UserPreset.xlsx","RowCount":10,"ColumnCount":5,"LastRecordIndex":10,"ColumnHeaders":[],"ResourceColums":[],"RecordIndexToDataArrayIndex":null,"ForeignKeyInfoMap":{},"CommentColumns":[],"IndexColumn":{"EnumName":null,"DataType":0,"MachineType":0,"StructType":0,"ColumnIndex":0,"Name":null}},"C:\\Git\\Game\\Content\\Table\\InGameMessage.xlsx":{"CachedLastWriteTime":"2023-03-02T18:35:57.2523419+09:00","FilePath":"C:\\Git\\Game\\Content\\Table\\InGameMessage.xlsx","RowCount":227,"ColumnCount":6,"LastRecordIndex":227,"ColumnHeaders":[],"ResourceColums":[],"RecordIndexToDataArrayIndex":null,"ForeignKeyInfoMap":{},"CommentColumns":[],"IndexColumn":{"EnumName":null,"DataType":0,"MachineType":0,"StructType":0,"ColumnIndex":0,"Name":null}},"C:\\Git\\Game\\Content\\Table\\GlobalControl.xlsx":{"CachedLastWriteTime":"2023-09-07T13:43:41.4534847+09:00","FilePath":"C:\\Git\\Game\\Content\\Table\\GlobalControl.xlsx","RowCount":106,"ColumnCount":4,"LastRecordIndex":106,"ColumnHeaders":[],"ResourceColums":[],"RecordIndexToDataArrayIndex":null,"ForeignKeyInfoMap":{},"CommentColumns":[],"IndexColumn":{"EnumName":null,"DataType":0,"MachineType":0,"StructType":0,"ColumnIndex":0,"Name":null}},"C:\\Git\\Game\\Content\\Table\\ItemMaterial.xlsx":{"CachedLastWriteTime":"2022-12-13T17:35:11.7612443+09:00","FilePath":"C:\\Git\\Game\\Content\\Table\\ItemMaterial.xlsx","RowCount":38,"ColumnCount":10,"LastRecordIndex":38,"ColumnHeaders":[],"ResourceColums":[],"RecordIndexToDataArrayIndex":null,"ForeignKeyInfoMap":{},"CommentColumns":[],"IndexColumn":{"EnumName":null,"DataType":0,"MachineType":0,"StructType":0,"ColumnIndex":0,"Name":null}},"C:\\Git\\Game\\Content\\Table\\InGameItem.xlsx":{"CachedLastWriteTime":"2023-09-26T17:15:48.579606+09:00","FilePath":"C:\\Git\\Game\\Content\\Table\\InGameItem.xlsx","RowCount":198,"ColumnCount":43,"LastRecordIndex":190,"ColumnHeaders":[],"ResourceColums":[],"RecordIndexToDataArrayIndex":null,"ForeignKeyInfoMap":{},"CommentColumns":[],"IndexColumn":{"EnumName":null,"DataType":0,"MachineType":0,"StructType":0,"ColumnIndex":0,"Name":null}},"C:\\Git\\Game\\Content\\Table\\OperatorEvent.xlsx":{"CachedLastWriteTime":"2023-07-26T15:16:39.1738026+09:00","FilePath":"C:\\Git\\Game\\Content\\Table\\OperatorEvent.xlsx","RowCount":162,"ColumnCount":12,"LastRecordIndex":94,"ColumnHeaders":[],"ResourceColums":[],"RecordIndexToDataArrayIndex":null,"ForeignKeyInfoMap":{},"CommentColumns":[],"IndexColumn":{"EnumName":null,"DataType":0,"MachineType":0,"StructType":0,"ColumnIndex":0,"Name":null}},"C:\\Git\\Game\\Content\\Table\\DroidBasic.xlsx":{"CachedLastWriteTime":"2024-01-11T10:42:27.966327+09:00","FilePath":"C:\\Git\\Game\\Content\\Table\\DroidBasic.xlsx","RowCount":17,"ColumnCount":29,"LastRecordIndex":17,"ColumnHeaders":[],"ResourceColums":[],"RecordIndexToDataArrayIndex":null,"ForeignKeyInfoMap":{},"CommentColumns":[],"IndexColumn":{"EnumName":null,"DataType":0,"MachineType":0,"StructType":0,"ColumnIndex":0,"Name":null}},"C:\\Git\\Game\\Content\\Table\\ItemEquipment.xlsx":{"CachedLastWriteTime":"2024-01-11T10:42:27.9693274+09:00","FilePath":"C:\\Git\\Game\\Content\\Table\\ItemEquipment.xlsx","RowCount":588,"ColumnCount":62,"LastRecordIndex":209,"ColumnHeaders":[],"ResourceColums":[],"RecordIndexToDataArrayIndex":null,"ForeignKeyInfoMap":{},"CommentColumns":[],"IndexColumn":{"EnumName":null,"DataType":0,"MachineType":0,"StructType":0,"ColumnIndex":0,"Name":null}},"C:\\Git\\Game\\Content\\Table\\SeasonPass.xlsx":{"CachedLastWriteTime":"2023-04-28T15:27:50.4225068+09:00","FilePath":"C:\\Git\\Game\\Content\\Table\\SeasonPass.xlsx","RowCount":104,"ColumnCount":13,"LastRecordIndex":104,"ColumnHeaders":[],"ResourceColums":[],"RecordIndexToDataArrayIndex":null,"ForeignKeyInfoMap":{},"CommentColumns":[],"IndexColumn":{"EnumName":null,"DataType":0,"MachineType":0,"StructType":0,"ColumnIndex":0,"Name":null}},"C:\\Git\\Game\\Content\\Table\\JourneyReward.xlsx":{"CachedLastWriteTime":"2023-09-13T12:37:55.8961055+09:00","FilePath":"C:\\Git\\Game\\Content\\Table\\JourneyReward.xlsx","RowCount":63,"ColumnCount":24,"LastRecordIndex":3,"ColumnHeaders":[],"ResourceColums":[],"RecordIndexToDataArrayIndex":null,"ForeignKeyInfoMap":{},"CommentColumns":[],"IndexColumn":{"EnumName":null,"DataType":0,"MachineType":0,"StructType":0,"ColumnIndex":0,"Name":null}},"C:\\Git\\Game\\Content\\Table\\Enum.xlsx":{"CachedLastWriteTime":"2023-09-26T17:15:48.5836072+09:00","FilePath":"C:\\Git\\Game\\Content\\Table\\Enum.xlsx","RowCount":1123,"ColumnCount":8,"LastRecordIndex":1112,"ColumnHeaders":[],"ResourceColums":[],"RecordIndexToDataArrayIndex":null,"ForeignKeyInfoMap":{},"CommentColumns":[],"IndexColumn":{"EnumName":null,"DataType":0,"MachineType":0,"StructType":0,"ColumnIndex":0,"Name":null}},"C:\\Git\\Game\\Content\\Table\\StatDefine.xlsx":{"CachedLastWriteTime":"2023-04-28T15:21:44.9645556+09:00","FilePath":"C:\\Git\\Game\\Content\\Table\\StatDefine.xlsx","RowCount":19,"ColumnCount":9,"LastRecordIndex":3,"ColumnHeaders":[],"ResourceColums":[],"RecordIndexToDataArrayIndex":null,"ForeignKeyInfoMap":{},"CommentColumns":[],"IndexColumn":{"EnumName":null,"DataType":0,"MachineType":0,"StructType":0,"ColumnIndex":0,"Name":null}},"C:\\Git\\Game\\Content\\Table\\IngamePerk.xlsx":{"CachedLastWriteTime":"2024-01-11T10:42:27.8002868+09:00","FilePath":"C:\\Git\\Game\\Content\\Table\\IngamePerk.xlsx","RowCount":324,"ColumnCount":17,"LastRecordIndex":324,"ColumnHeaders":[],"ResourceColums":[],"RecordIndexToDataArrayIndex":null,"ForeignKeyInfoMap":{},"CommentColumns":[],"IndexColumn":{"EnumName":null,"DataType":0,"MachineType":0,"StructType":0,"ColumnIndex":0,"Name":null}},"C:\\Git\\Game\\Content\\Table\\MonsterBasic.xlsx":{"CachedLastWriteTime":"2023-09-26T17:15:48.5816068+09:00","FilePath":"C:\\Git\\Game\\Content\\Table\\MonsterBasic.xlsx","RowCount":329,"ColumnCount":30,"LastRecordIndex":329,"ColumnHeaders":[],"ResourceColums":[],"RecordIndexToDataArrayIndex":null,"ForeignKeyInfoMap":{},"CommentColumns":[],"IndexColumn":{"EnumName":null,"DataType":0,"MachineType":0,"StructType":0,"ColumnIndex":0,"Name":null}},"C:\\Git\\Game\\Content\\Table\\Tutorial.xlsx":{"CachedLastWriteTime":"2023-03-22T11:07:31.2760038+09:00","FilePath":"C:\\Git\\Game\\Content\\Table\\Tutorial.xlsx","RowCount":194,"ColumnCount":8,"LastRecordIndex":49,"ColumnHeaders":[],"ResourceColums":[],"RecordIndexToDataArrayIndex":null,"ForeignKeyInfoMap":{},"CommentColumns":[],"IndexColumn":{"EnumName":null,"DataType":0,"MachineType":0,"StructType":0,"ColumnIndex":0,"Name":null}},"C:\\Git\\Game\\Content\\Table\\WeaponDrop.xlsx":{"CachedLastWriteTime":"2024-01-11T10:42:28.2139853+09:00","FilePath":"C:\\Git\\Game\\Content\\Table\\WeaponDrop.xlsx","RowCount":459,"ColumnCount":7,"LastRecordIndex":459,"ColumnHeaders":[],"ResourceColums":[],"RecordIndexToDataArrayIndex":null,"ForeignKeyInfoMap":{},"CommentColumns":[],"IndexColumn":{"EnumName":null,"DataType":0,"MachineType":0,"StructType":0,"ColumnIndex":0,"Name":null}},"C:\\Git\\Game\\Content\\Table\\ExplorationMission.xlsx":{"CachedLastWriteTime":"2023-05-17T11:48:09.2632142+09:00","FilePath":"C:\\Git\\Game\\Content\\Table\\ExplorationMission.xlsx","RowCount":196,"ColumnCount":11,"LastRecordIndex":22,"ColumnHeaders":[],"ResourceColums":[],"RecordIndexToDataArrayIndex":null,"ForeignKeyInfoMap":{},"CommentColumns":[],"IndexColumn":{"EnumName":null,"DataType":0,"MachineType":0,"StructType":0,"ColumnIndex":0,"Name":null}},"C:\\Git\\Game\\Content\\Table\\Trophy.xlsx":{"CachedLastWriteTime":"2024-01-11T10:42:28.3770264+09:00","FilePath":"C:\\Git\\Game\\Content\\Table\\Trophy.xlsx","RowCount":125,"ColumnCount":12,"LastRecordIndex":125,"ColumnHeaders":[],"ResourceColums":[],"RecordIndexToDataArrayIndex":null,"ForeignKeyInfoMap":{},"CommentColumns":[],"IndexColumn":{"EnumName":null,"DataType":0,"MachineType":0,"StructType":0,"ColumnIndex":0,"Name":null}},"C:\\Git\\Game\\Content\\Table\\TeamBasic.xlsx":{"CachedLastWriteTime":"2022-12-13T17:35:11.9052084+09:00","FilePath":"C:\\Git\\Game\\Content\\Table\\TeamBasic.xlsx","RowCount":104,"ColumnCount":13,"LastRecordIndex":104,"ColumnHeaders":[],"ResourceColums":[],"RecordIndexToDataArrayIndex":null,"ForeignKeyInfoMap":{},"CommentColumns":[],"IndexColumn":{"EnumName":null,"DataType":0,"MachineType":0,"StructType":0,"ColumnIndex":0,"Name":null}},"C:\\Git\\Game\\Content\\Table\\GameModeInfo.xlsx":{"CachedLastWriteTime":"2023-07-04T17:33:57.5138352+09:00","FilePath":"C:\\Git\\Game\\Content\\Table\\GameModeInfo.xlsx","RowCount":18,"ColumnCount":29,"LastRecordIndex":3,"ColumnHeaders":[],"ResourceColums":[],"RecordIndexToDataArrayIndex":null,"ForeignKeyInfoMap":{},"CommentColumns":[],"IndexColumn":{"EnumName":null,"DataType":0,"MachineType":0,"StructType":0,"ColumnIndex":0,"Name":null}},"C:\\Git\\Game\\Content\\Table\\SkillTree.xlsx":{"CachedLastWriteTime":"2023-04-28T15:27:50.4335096+09:00","FilePath":"C:\\Git\\Game\\Content\\Table\\SkillTree.xlsx","RowCount":25,"ColumnCount":20,"LastRecordIndex":25,"ColumnHeaders":[],"ResourceColums":[],"RecordIndexToDataArrayIndex":null,"ForeignKeyInfoMap":{},"CommentColumns":[],"IndexColumn":{"EnumName":null,"DataType":0,"MachineType":0,"StructType":0,"ColumnIndex":0,"Name":null}},"C:\\Git\\Game\\Content\\Table\\String.xlsx":{"CachedLastWriteTime":"2024-01-11T10:42:27.9753295+09:00","FilePath":"C:\\Git\\Game\\Content\\Table\\String.xlsx","RowCount":4058,"ColumnCount":37,"LastRecordIndex":4058,"ColumnHeaders":[],"ResourceColums":[],"RecordIndexToDataArrayIndex":null,"ForeignKeyInfoMap":{},"CommentColumns":[],"IndexColumn":{"EnumName":null,"DataType":0,"MachineType":0,"StructType":0,"ColumnIndex":0,"Name":null}},"C:\\Git\\Game\\Content\\Table\\Stage.xlsx":{"CachedLastWriteTime":"2023-09-26T17:16:02.4090615+09:00","FilePath":"C:\\Git\\Game\\Content\\Table\\Stage.xlsx","RowCount":134,"ColumnCount":17,"LastRecordIndex":114,"ColumnHeaders":[],"ResourceColums":[],"RecordIndexToDataArrayIndex":null,"ForeignKeyInfoMap":{},"CommentColumns":[],"IndexColumn":{"EnumName":null,"DataType":0,"MachineType":0,"StructType":0,"ColumnIndex":0,"Name":null}},"C:\\Git\\Game\\Content\\Table\\Character.xlsx":{"CachedLastWriteTime":"2024-01-11T10:42:27.7992868+09:00","FilePath":"C:\\Git\\Game\\Content\\Table\\Character.xlsx","RowCount":20,"ColumnCount":42,"LastRecordIndex":20,"ColumnHeaders":[],"ResourceColums":[],"RecordIndexToDataArrayIndex":null,"ForeignKeyInfoMap":{},"CommentColumns":[],"IndexColumn":{"EnumName":null,"DataType":0,"MachineType":0,"StructType":0,"ColumnIndex":0,"Name":null}},"C:\\Git\\Game\\Content\\Table\\Achievement.xlsx":{"CachedLastWriteTime":"2024-01-11T10:42:28.2099849+09:00","FilePath":"C:\\Git\\Game\\Content\\Table\\Achievement.xlsx","RowCount":324,"ColumnCount":10,"LastRecordIndex":324,"ColumnHeaders":[],"ResourceColums":[],"RecordIndexToDataArrayIndex":null,"ForeignKeyInfoMap":{},"CommentColumns":[],"IndexColumn":{"EnumName":null,"DataType":0,"MachineType":0,"StructType":0,"ColumnIndex":0,"Name":null}},"C:\\Git\\Game\\Content\\Table\\DroidUpgrade.xlsx":{"CachedLastWriteTime":"2023-02-09T15:15:42.7605822+09:00","FilePath":"C:\\Git\\Game\\Content\\Table\\DroidUpgrade.xlsx","RowCount":14,"ColumnCount":11,"LastRecordIndex":14,"ColumnHeaders":[],"ResourceColums":[],"RecordIndexToDataArrayIndex":null,"ForeignKeyInfoMap":{},"CommentColumns":[],"IndexColumn":{"EnumName":null,"DataType":0,"MachineType":0,"StructType":0,"ColumnIndex":0,"Name":null}},"C:\\Git\\Game\\Content\\Table\\Config.xlsx":{"CachedLastWriteTime":"2023-09-26T17:16:02.4360679+09:00","FilePath":"C:\\Git\\Game\\Content\\Table\\Config.xlsx","RowCount":107,"ColumnCount":17,"LastRecordIndex":3,"ColumnHeaders":[],"ResourceColums":[],"RecordIndexToDataArrayIndex":null,"ForeignKeyInfoMap":{},"CommentColumns":[],"IndexColumn":{"EnumName":null,"DataType":0,"MachineType":0,"StructType":0,"ColumnIndex":0,"Name":null}},"C:\\Git\\Game\\Content\\Table\\MonsterStat.xlsx":{"CachedLastWriteTime":"2023-05-31T12:42:04.7224977+09:00","FilePath":"C:\\Git\\Game\\Content\\Table\\MonsterStat.xlsx","RowCount":304,"ColumnCount":17,"LastRecordIndex":304,"ColumnHeaders":[],"ResourceColums":[],"RecordIndexToDataArrayIndex":null,"ForeignKeyInfoMap":{},"CommentColumns":[],"IndexColumn":{"EnumName":null,"DataType":0,"MachineType":0,"StructType":0,"ColumnIndex":0,"Name":null}},"C:\\Git\\Game\\Content\\Table\\DroidOption.xlsx":{"CachedLastWriteTime":"2024-01-11T10:42:28.3720243+09:00","FilePath":"C:\\Git\\Game\\Content\\Table\\DroidOption.xlsx","RowCount":63,"ColumnCount":19,"LastRecordIndex":63,"ColumnHeaders":[],"ResourceColums":[],"RecordIndexToDataArrayIndex":null,"ForeignKeyInfoMap":{},"CommentColumns":[],"IndexColumn":{"EnumName":null,"DataType":0,"MachineType":0,"StructType":0,"ColumnIndex":0,"Name":null}},"C:\\Git\\Game\\Content\\Table\\ItemEquipmentBullet.xlsx":{"CachedLastWriteTime":"2023-10-18T18:06:22.3489265+09:00","FilePath":"C:\\Git\\Game\\Content\\Table\\ItemEquipmentBullet.xlsx","RowCount":54,"ColumnCount":15,"LastRecordIndex":50,"ColumnHeaders":[],"ResourceColums":[],"RecordIndexToDataArrayIndex":null,"ForeignKeyInfoMap":{},"CommentColumns":[],"IndexColumn":{"EnumName":null,"DataType":0,"MachineType":0,"StructType":0,"ColumnIndex":0,"Name":null}},"C:\\Git\\Game\\Content\\Table\\Skin.xlsx":{"CachedLastWriteTime":"2023-10-19T10:37:03.3935197+09:00","FilePath":"C:\\Git\\Game\\Content\\Table\\Skin.xlsx","RowCount":246,"ColumnCount":15,"LastRecordIndex":246,"ColumnHeaders":[],"ResourceColums":[],"RecordIndexToDataArrayIndex":null,"ForeignKeyInfoMap":{},"CommentColumns":[],"IndexColumn":{"EnumName":null,"DataType":0,"MachineType":0,"StructType":0,"ColumnIndex":0,"Name":null}},"C:\\Git\\Game\\Content\\Table\\MonsterStatMultipleMonsterGrade.xlsx":{"CachedLastWriteTime":"2023-01-03T14:42:00.0664371+09:00","FilePath":"C:\\Git\\Game\\Content\\Table\\MonsterStatMultipleMonsterGrade.xlsx","RowCount":12,"ColumnCount":10,"LastRecordIndex":3,"ColumnHeaders":[],"ResourceColums":[],"RecordIndexToDataArrayIndex":null,"ForeignKeyInfoMap":{},"CommentColumns":[],"IndexColumn":{"EnumName":null,"DataType":0,"MachineType":0,"StructType":0,"ColumnIndex":0,"Name":null}},"C:\\Git\\Game\\Content\\Table\\ChallengeReward.xlsx":{"CachedLastWriteTime":"2023-02-23T10:38:35.2592155+09:00","FilePath":"C:\\Git\\Game\\Content\\Table\\ChallengeReward.xlsx","RowCount":19,"ColumnCount":12,"LastRecordIndex":19,"ColumnHeaders":[],"ResourceColums":[],"RecordIndexToDataArrayIndex":null,"ForeignKeyInfoMap":{},"CommentColumns":[],"IndexColumn":{"EnumName":null,"DataType":0,"MachineType":0,"StructType":0,"ColumnIndex":0,"Name":null}},"C:\\Git\\Game\\Content\\Table\\SkillPassive.xlsx":{"CachedLastWriteTime":"2024-01-11T10:42:27.8022876+09:00","FilePath":"C:\\Git\\Game\\Content\\Table\\SkillPassive.xlsx","RowCount":1814,"ColumnCount":17,"LastRecordIndex":1814,"ColumnHeaders":[],"ResourceColums":[],"RecordIndexToDataArrayIndex":null,"ForeignKeyInfoMap":{},"CommentColumns":[],"IndexColumn":{"EnumName":null,"DataType":0,"MachineType":0,"StructType":0,"ColumnIndex":0,"Name":null}},"C:\\Git\\Game\\Content\\Table\\DLC.xlsx":{"CachedLastWriteTime":"2022-12-13T17:30:00.4298815+09:00","FilePath":"C:\\Git\\Game\\Content\\Table\\DLC.xlsx","RowCount":10,"ColumnCount":11,"LastRecordIndex":10,"ColumnHeaders":[],"ResourceColums":[],"RecordIndexToDataArrayIndex":null,"ForeignKeyInfoMap":{},"CommentColumns":[],"IndexColumn":{"EnumName":null,"DataType":0,"MachineType":0,"StructType":0,"ColumnIndex":0,"Name":null}},"C:\\Git\\Game\\Content\\Table\\ItemCash.xlsx":{"CachedLastWriteTime":"2023-03-06T09:56:33.8164645+09:00","FilePath":"C:\\Git\\Game\\Content\\Table\\ItemCash.xlsx","RowCount":18,"ColumnCount":8,"LastRecordIndex":18,"ColumnHeaders":[],"ResourceColums":[],"RecordIndexToDataArrayIndex":null,"ForeignKeyInfoMap":{},"CommentColumns":[],"IndexColumn":{"EnumName":null,"DataType":0,"MachineType":0,"StructType":0,"ColumnIndex":0,"Name":null}},"C:\\Git\\Game\\Content\\Table\\SkillActive.xlsx":{"CachedLastWriteTime":"2024-01-11T10:42:28.2129853+09:00","FilePath":"C:\\Git\\Game\\Content\\Table\\SkillActive.xlsx","RowCount":1405,"ColumnCount":14,"LastRecordIndex":1405,"ColumnHeaders":[],"ResourceColums":[],"RecordIndexToDataArrayIndex":null,"ForeignKeyInfoMap":{},"CommentColumns":[],"IndexColumn":{"EnumName":null,"DataType":0,"MachineType":0,"StructType":0,"ColumnIndex":0,"Name":null}},"C:\\Git\\Game\\Content\\Table\\MonsterStatMultipleMonsterType.xlsx":{"CachedLastWriteTime":"2023-09-26T17:15:48.5756051+09:00","FilePath":"C:\\Git\\Game\\Content\\Table\\MonsterStatMultipleMonsterType.xlsx","RowCount":208,"ColumnCount":10,"LastRecordIndex":3,"ColumnHeaders":[],"ResourceColums":[],"RecordIndexToDataArrayIndex":null,"ForeignKeyInfoMap":{},"CommentColumns":[],"IndexColumn":{"EnumName":null,"DataType":0,"MachineType":0,"StructType":0,"ColumnIndex":0,"Name":null}},"C:\\Git\\Game\\Content\\Table\\InGameDrop.xlsx":{"CachedLastWriteTime":"2023-08-02T16:46:29.9791693+09:00","FilePath":"C:\\Git\\Game\\Content\\Table\\InGameDrop.xlsx","RowCount":51,"ColumnCount":7,"LastRecordIndex":51,"ColumnHeaders":[],"ResourceColums":[],"RecordIndexToDataArrayIndex":null,"ForeignKeyInfoMap":{},"CommentColumns":[],"IndexColumn":{"EnumName":null,"DataType":0,"MachineType":0,"StructType":0,"ColumnIndex":0,"Name":null}},"C:\\Git\\Game\\Content\\Table\\OperatorScript.xlsx":{"CachedLastWriteTime":"2023-07-26T15:16:12.9943171+09:00","FilePath":"C:\\Git\\Game\\Content\\Table\\OperatorScript.xlsx","RowCount":298,"ColumnCount":10,"LastRecordIndex":298,"ColumnHeaders":[],"ResourceColums":[],"RecordIndexToDataArrayIndex":null,"ForeignKeyInfoMap":{},"CommentColumns":[],"IndexColumn":{"EnumName":null,"DataType":0,"MachineType":0,"StructType":0,"ColumnIndex":0,"Name":null}},"C:\\Git\\Game\\Content\\Table\\JourneyStage.xlsx":{"CachedLastWriteTime":"2023-09-13T14:28:55.3306644+09:00","FilePath":"C:\\Git\\Game\\Content\\Table\\JourneyStage.xlsx","RowCount":35,"ColumnCount":7,"LastRecordIndex":3,"ColumnHeaders":[],"ResourceColums":[],"RecordIndexToDataArrayIndex":null,"ForeignKeyInfoMap":{},"CommentColumns":[],"IndexColumn":{"EnumName":null,"DataType":0,"MachineType":0,"StructType":0,"ColumnIndex":0,"Name":null}},"C:\\Git\\Game\\Content\\Table\\Gimmick.xlsx":{"CachedLastWriteTime":"2023-01-19T17:37:47.9548174+09:00","FilePath":"C:\\Git\\Game\\Content\\Table\\Gimmick.xlsx","RowCount":39,"ColumnCount":16,"LastRecordIndex":39,"ColumnHeaders":[],"ResourceColums":[],"RecordIndexToDataArrayIndex":null,"ForeignKeyInfoMap":{},"CommentColumns":[],"IndexColumn":{"EnumName":null,"DataType":0,"MachineType":0,"StructType":0,"ColumnIndex":0,"Name":null}},"C:\\Git\\Game\\Content\\Table\\WeaponPassive.xlsx":{"CachedLastWriteTime":"2023-08-01T17:51:07.9102248+09:00","FilePath":"C:\\Git\\Game\\Content\\Table\\WeaponPassive.xlsx","RowCount":130,"ColumnCount":13,"LastRecordIndex":130,"ColumnHeaders":[],"ResourceColums":[],"RecordIndexToDataArrayIndex":null,"ForeignKeyInfoMap":{},"CommentColumns":[],"IndexColumn":{"EnumName":null,"DataType":0,"MachineType":0,"StructType":0,"ColumnIndex":0,"Name":null}},"C:\\Git\\Game\\Content\\Table\\Operator.xlsx":{"CachedLastWriteTime":"2023-08-02T13:49:49.5437258+09:00","FilePath":"C:\\Git\\Game\\Content\\Table\\Operator.xlsx","RowCount":194,"ColumnCount":14,"LastRecordIndex":5,"ColumnHeaders":[],"ResourceColums":[],"RecordIndexToDataArrayIndex":null,"ForeignKeyInfoMap":{},"CommentColumns":[],"IndexColumn":{"EnumName":null,"DataType":0,"MachineType":0,"StructType":0,"ColumnIndex":0,"Name":null}},"C:\\Git\\Game\\Content\\Table\\DroidOptionGroup.xlsx":{"CachedLastWriteTime":"2024-01-11T10:42:28.2109845+09:00","FilePath":"C:\\Git\\Game\\Content\\Table\\DroidOptionGroup.xlsx","RowCount":202,"ColumnCount":7,"LastRecordIndex":202,"ColumnHeaders":[],"ResourceColums":[],"RecordIndexToDataArrayIndex":null,"ForeignKeyInfoMap":{},"CommentColumns":[],"IndexColumn":{"EnumName":null,"DataType":0,"MachineType":0,"StructType":0,"ColumnIndex":0,"Name":null}},"C:\\Git\\Game\\Content\\Table\\StageMap.xlsx":{"CachedLastWriteTime":"2023-09-26T17:15:48.572604+09:00","FilePath":"C:\\Git\\Game\\Content\\Table\\StageMap.xlsx","RowCount":890,"ColumnCount":32,"LastRecordIndex":890,"ColumnHeaders":[],"ResourceColums":[],"RecordIndexToDataArrayIndex":null,"ForeignKeyInfoMap":{},"CommentColumns":[],"IndexColumn":{"EnumName":null,"DataType":0,"MachineType":0,"StructType":0,"ColumnIndex":0,"Name":null}},"C:\\Git\\Game\\Content\\Table\\WeaponGrade.xlsx":{"CachedLastWriteTime":"2023-03-20T18:23:05.9926211+09:00","FilePath":"C:\\Git\\Game\\Content\\Table\\WeaponGrade.xlsx","RowCount":8,"ColumnCount":11,"LastRecordIndex":8,"ColumnHeaders":[],"ResourceColums":[],"RecordIndexToDataArrayIndex":null,"ForeignKeyInfoMap":{},"CommentColumns":[],"IndexColumn":{"EnumName":null,"DataType":0,"MachineType":0,"StructType":0,"ColumnIndex":0,"Name":null}}}